[
    {
        "Questions": ["Please explain the revolving credit of Lyft for year 2023 and its long term benefits?"],
        "reference":"/content/drive/MyDrive/RAG/data/10k/lyft_10k_2023.pdf",
         "retrieved_contexts":["Revolving Credit Facility & Other Financings\nOn November 3, 2022, Lyft, Inc. entered into a revolving credit agreement (the “Existing Revolving Credit Agreement”) by and among the Company,\nas the borrower, JPMorgan Chase Bank, N.A., as administrative agent, and certain lenders party thereto from time to time. On December 12, 2023, the\nCompany entered into Amendment No. 1 to Revolving Credit Agreement (the “Credit Agreement Amendment”) with the other loan parties party thereto,\nJPMorgan Chase Bank, N.A., as administrative agent and certain lenders party thereto, which amends the Existing Revolving Credit Agreement (the Existing\nRevolving Credit Agreement as amended by the Credit Agreement Amendment, the Revolving Credit Agreement) to"],
        "Ground_Truth": ["In 2023, Lyft entered into a revolving credit agreement with certain lenders for a 1.25 billion.  The long-term benefits of this revolving credit facility include providing Lyft with financial flexibility and access to capital when needed. It allows Lyft to borrow funds, repay them, and borrow again up to the agreed-upon limit, providing liquidity for operational needs, investments, or other strategic initiatives. Additionally, having a revolving credit facility in place can help Lyft manage its cash flow, take advantage of opportunities for growth, and navigate any unforeseen financial challenges."],
        "user_input":["In 2023, Lyft entered into a revolving credit agreement with certain"]
    }
]
